bw_env/__init__.py
bw_env/__main__.py
bw_env/_generate.py
bw_env/_main.py
bw_env/_run.py
bw_env/_utils.py
bwenv-1.0.0.dist-info/LICENSE
bwenv-1.0.0.dist-info/METADATA
bwenv-1.0.0.dist-info/WHEEL
bwenv-1.0.0.dist-info/entry_points.txt
bwenv-1.0.0.dist-info/top_level.txt
bwenv-1.0.0.dist-info/RECORD
