Metadata-Version: 2.1
Name: bwenv
Version: 1.0.0
Summary: Securely use and share environment variables in your local development using Bitwarden
Author-email: Arkin Modi <arkinmodi@gmail.com>
License: MIT License
Project-URL: Homepage, https://github.com/arkinmodi/bitwarden-env
Classifier: Intended Audience :: Developers
Classifier: License :: OSI Approved :: MIT License
Classifier: Programming Language :: Python :: 3 :: Only
Classifier: Programming Language :: Python :: 3
Classifier: Programming Language :: Python :: Implementation :: CPython
Classifier: Topic :: Software Development
Classifier: Topic :: Utilities
Requires-Python: >=3.8
License-File: LICENSE
Requires-Dist: python-dotenv (>=0.8.0)
